zun_tempest_plugin/__init__.py
zun_tempest_plugin/tests/__init__.py
zun_tempest_plugin/tests/tempest/README.rst
zun_tempest_plugin/tests/tempest/__init__.py
zun_tempest_plugin/tests/tempest/base.py
zun_tempest_plugin/tests/tempest/config.py
zun_tempest_plugin/tests/tempest/plugin.py
zun_tempest_plugin/tests/tempest/utils.py
zun_tempest_plugin/tests/tempest/api/__init__.py
zun_tempest_plugin/tests/tempest/api/api_microversion_fixture.py
zun_tempest_plugin/tests/tempest/api/clients.py
zun_tempest_plugin/tests/tempest/api/test_capsules.py
zun_tempest_plugin/tests/tempest/api/test_containers.py
zun_tempest_plugin/tests/tempest/api/test_services.py
zun_tempest_plugin/tests/tempest/api/common/__init__.py
zun_tempest_plugin/tests/tempest/api/common/base_model.py
zun_tempest_plugin/tests/tempest/api/common/datagen.py
zun_tempest_plugin/tests/tempest/api/models/__init__.py
zun_tempest_plugin/tests/tempest/api/models/capsule_model.py
zun_tempest_plugin/tests/tempest/api/models/container_model.py
zun_tempest_plugin/tests/tempest/api/models/host_model.py
zun_tempest_plugin/tests/tempest/api/models/service_model.py
zun_tempest_plugin-4.12.0.dist-info/AUTHORS
zun_tempest_plugin-4.12.0.dist-info/LICENSE
zun_tempest_plugin-4.12.0.dist-info/METADATA
zun_tempest_plugin-4.12.0.dist-info/WHEEL
zun_tempest_plugin-4.12.0.dist-info/entry_points.txt
zun_tempest_plugin-4.12.0.dist-info/pbr.json
zun_tempest_plugin-4.12.0.dist-info/top_level.txt
zun_tempest_plugin-4.12.0.dist-info/RECORD
